sbvirtualdisplay/__init__.py
sbvirtualdisplay/__version__.py
sbvirtualdisplay/abstractdisplay.py
sbvirtualdisplay/display.py
sbvirtualdisplay/easyprocess.py
sbvirtualdisplay/unicodeutil.py
sbvirtualdisplay/xauth.py
sbvirtualdisplay/xephyr.py
sbvirtualdisplay/xvfb.py
sbvirtualdisplay/xvnc.py
sbvirtualdisplay-1.3.1.dist-info/LICENSE
sbvirtualdisplay-1.3.1.dist-info/METADATA
sbvirtualdisplay-1.3.1.dist-info/WHEEL
sbvirtualdisplay-1.3.1.dist-info/top_level.txt
sbvirtualdisplay-1.3.1.dist-info/RECORD
