Metadata-Version: 2.1
Name: sbvirtualdisplay
Version: 1.3.1
Summary: A customized pyvirtualdisplay for SeleniumBase.
Home-page: https://github.com/mdmintz/sbVirtualDisplay
Author: Michael Mintz
Author-email: mdmintz@gmail.com
Maintainer: Michael Mintz
License: MIT
Project-URL: Changelog, https://github.com/mdmintz/sbVirtualDisplay/releases
Project-URL: Download, https://pypi.org/project/sbvirtualdisplay/#files
Project-URL: SeleniumBase, https://github.com/seleniumbase/SeleniumBase
Project-URL: PyPI, https://pypi.org/project/sbvirtualdisplay/
Project-URL: Source, https://github.com/mdmintz/sbVirtualDisplay
Platform: Windows
Platform: Linux
Platform: Mac OS-X
Classifier: Development Status :: 5 - Production/Stable
Classifier: Environment :: Console
Classifier: Environment :: MacOS X
Classifier: Environment :: Win32 (MS Windows)
Classifier: Environment :: Web Environment
Classifier: Framework :: Pytest
Classifier: Intended Audience :: Developers
Classifier: Intended Audience :: Information Technology
Classifier: License :: OSI Approved :: MIT License
Classifier: Operating System :: MacOS :: MacOS X
Classifier: Operating System :: Microsoft :: Windows
Classifier: Operating System :: POSIX :: Linux
Classifier: Programming Language :: Python
Classifier: Programming Language :: Python :: 3
Classifier: Programming Language :: Python :: 3.7
Classifier: Programming Language :: Python :: 3.8
Classifier: Programming Language :: Python :: 3.9
Classifier: Programming Language :: Python :: 3.10
Classifier: Programming Language :: Python :: 3.11
Classifier: Programming Language :: Python :: 3.12
Classifier: Programming Language :: Python :: 3.13
Classifier: Topic :: Internet
Classifier: Topic :: Scientific/Engineering
Classifier: Topic :: Software Development
Classifier: Topic :: Software Development :: Quality Assurance
Classifier: Topic :: Software Development :: Libraries
Classifier: Topic :: Software Development :: Testing
Classifier: Topic :: Software Development :: Testing :: Acceptance
Classifier: Topic :: Software Development :: Testing :: Traffic Generation
Classifier: Topic :: Utilities
Requires-Python: >=3.7
License-File: LICENSE
Provides-Extra: coverage
Requires-Dist: coverage==7.2.7; python_version < "3.8" and extra == "coverage"
Requires-Dist: coverage==7.3.2; python_version >= "3.8" and extra == "coverage"
Requires-Dist: pytest-cov==4.1.0; extra == "coverage"
Provides-Extra: flake8
Requires-Dist: flake8==5.0.4; python_version < "3.9" and extra == "flake8"
Requires-Dist: flake8==6.1.0; python_version >= "3.9" and extra == "flake8"
Requires-Dist: mccabe==0.7.0; extra == "flake8"
Requires-Dist: pyflakes==2.5.0; python_version < "3.9" and extra == "flake8"
Requires-Dist: pyflakes==3.1.0; python_version >= "3.9" and extra == "flake8"
Requires-Dist: pycodestyle==2.9.1; python_version < "3.9" and extra == "flake8"
Requires-Dist: pycodestyle==2.11.1; python_version >= "3.9" and extra == "flake8"
